gpnam/__init__.py
gpnam/data.py
gpnam/download_datasets.py
gpnam/model.py
gpnam/sklearn.py
gpnam/trainer.py
gpnam/utils.py
gpnam-0.1.0.dist-info/LICENSE
gpnam-0.1.0.dist-info/METADATA
gpnam-0.1.0.dist-info/WHEEL
gpnam-0.1.0.dist-info/top_level.txt
gpnam-0.1.0.dist-info/RECORD
