Metadata-Version: 2.1
Name: gpnam
Version: 0.1.0
Summary: GPNAM - an interpretable Gaussian Process Neural Additive Model.
Author-email: Wei Zhang <wz2363@columbia.edu>
Project-URL: Homepage, https://github.com/Wei2624/GPNAM
Project-URL: Issues, https://github.com/Wei2624/GPNAM/issues
Classifier: Programming Language :: Python :: 3.7
Classifier: Development Status :: 3 - Alpha
Classifier: License :: OSI Approved :: MIT License
Classifier: Operating System :: OS Independent
Requires-Python: >=3.7
License-File: LICENSE
Requires-Dist: torch >=1.13.1
Requires-Dist: numpy >=1.21.5
Requires-Dist: scipy >=1.7.3
Requires-Dist: scikit-learn >=1.0.2
Requires-Dist: matplotlib >=3.5.3
Requires-Dist: tqdm >=4.66.2
Requires-Dist: pandas >=1.3.5
Requires-Dist: requests >=2.28.1
